{
  "project_count_by_sdg": [
    34,
    6,
    60,
    61,
    28,
    19,
    38,
    143,
    102,
    39,
    115,
    2,
    19,
    0,
    0,
    7,
    79
  ],
  "total_amount_usd_by_sdg": [
    3576639630.1090007,
    449781752.666,
    7127279789.665001,
    6702059300.94,
    2076997368.3200002,
    1521559373.8199997,
    3226141797.022,
    12292305125.367008,
    9774583880.495003,
    4996942489.160999,
    11784401744.791998,
    165236668.15,
    3969783261.56,
    0.0,
    0.0,
    728608476.86,
    8171433221.155
  ],
  "sdg_labels": [
    "SDG 1",
    "SDG 2",
    "SDG 3",
    "SDG 4",
    "SDG 5",
    "SDG 6",
    "SDG 7",
    "SDG 8",
    "SDG 9",
    "SDG 10",
    "SDG 11",
    "SDG 12",
    "SDG 13",
    "SDG 14",
    "SDG 15",
    "SDG 16",
    "SDG 17"
  ],
  "per_year": {
    "2016": {
      "project_count_by_sdg": [
        2,
        0,
        2,
        7,
        0,
        1,
        3,
        16,
        8,
        2,
        10,
        0,
        0,
        0,
        0,
        0,
        5
      ],
      "total_amount_usd_by_sdg": [
        128400761.11,
        0.0,
        27672577.825999998,
        664916699.96,
        0.0,
        12175934.24,
        216953010.09,
        1594493934.1419997,
        699230696.4,
        239091072.41,
        1636054285.1600003,
        0.0,
        0.0,
        0.0,
        0.0,
        0.0,
        655286642.88
      ]
    },
    "2017": {
      "project_count_by_sdg": [
        3,
        1,
        3,
        3,
        1,
        1,
        4,
        22,
        13,
        1,
        14,
        0,
        1,
        0,
        0,
        0,
        1
      ],
      "total_amount_usd_by_sdg": [
        282420294.02,
        90374494.12,
        429278847.02,
        329866903.54,
        33890435.29,
        90374494.12,
        286939018.78,
        2491624802.2499995,
        1455029355.06,
        112968117.6,
        1018972420.98,
        0.0,
        395388411.8,
        0.0,
        0.0,
        0.0,
        39538841.18
      ]
    },
    "2018": {
      "project_count_by_sdg": [
        2,
        0,
        4,
        5,
        2,
        1,
        5,
        16,
        14,
        3,
        4,
        0,
        0,
        0,
        0,
        2,
        3
      ],
      "total_amount_usd_by_sdg": [
        413334078.39,
        0.0,
        359010171.02,
        459391304.35,
        238552811.02,
        59047725.49,
        428096009.865,
        1486821727.938,
        1590070894.21,
        246819492.589,
        354286352.98,
        0.0,
        0.0,
        0.0,
        0.0,
        445219850.2,
        188952721.57
      ]
    },
    "2019": {
      "project_count_by_sdg": [
        1,
        0,
        5,
        4,
        0,
        4,
        3,
        14,
        9,
        0,
        12,
        0,
        3,
        0,
        0,
        1,
        9
      ],
      "total_amount_usd_by_sdg": [
        167921176.5,
        0.0,
        220963571.4,
        906774352.9,
        0.0,
        419802941.23,
        324647607.89,
        934761215.819,
        1040311669.3,
        0.0,
        1014467800.9,
        0.0,
        324647607.89,
        0.0,
        0.0,
        11194745.1,
        745793918.51
      ]
    },
    "2020": {
      "project_count_by_sdg": [
        3,
        1,
        19,
        7,
        1,
        1,
        5,
        10,
        12,
        2,
        13,
        1,
        1,
        0,
        0,
        0,
        15
      ],
      "total_amount_usd_by_sdg": [
        342658832.70000005,
        228439221.8,
        3320364088.8099995,
        950307162.5899999,
        2284392.218,
        91375688.72,
        618499193.01,
        813243629.548,
        790628146.53,
        399768638.1,
        971209351.3599999,
        57109805.45,
        342658832.7,
        0.0,
        0.0,
        0.0,
        1449789521.1399999
      ]
    },
    "2021": {
      "project_count_by_sdg": [
        2,
        0,
        9,
        10,
        5,
        3,
        4,
        15,
        12,
        3,
        11,
        0,
        0,
        0,
        0,
        0,
        9
      ],
      "total_amount_usd_by_sdg": [
        201065852.7,
        0.0,
        755617301.88,
        913141227.72,
        531760043.426,
        211473967.43,
        353639352.7,
        1068724144.1159999,
        1433836077.911,
        171024248.826,
        1330582848.81,
        0.0,
        0.0,
        0.0,
        0.0,
        0.0,
        644120372.8659999
      ]
    },
    "2022": {
      "project_count_by_sdg": [
        2,
        0,
        2,
        5,
        4,
        0,
        3,
        10,
        5,
        8,
        11,
        0,
        3,
        0,
        0,
        2,
        6
      ],
      "total_amount_usd_by_sdg": [
        214821922.153,
        0.0,
        304331056.39,
        234303321.95999998,
        293800570.003,
        0.0,
        358036536.92999995,
        1197316301.4559999,
        314335018.45,
        1711204036.95,
        1291037630.22,
        0.0,
        652890155.5699999,
        0.0,
        0.0,
        136896322.94,
        594972480.49
      ]
    },
    "2023": {
      "project_count_by_sdg": [
        3,
        0,
        7,
        6,
        7,
        3,
        4,
        14,
        8,
        8,
        14,
        1,
        3,
        0,
        0,
        0,
        13
      ],
      "total_amount_usd_by_sdg": [
        486570882.29999995,
        0.0,
        747264748.3989999,
        615458102.77,
        661736399.9,
        207603576.48000002,
        346005960.72,
        1351261403.6550002,
        647896161.604,
        724125599.765,
        1180420960.5019999,
        108126862.7,
        389256705.87,
        0.0,
        0.0,
        0.0,
        1550755465.439
      ]
    },
    "2024": {
      "project_count_by_sdg": [
        8,
        1,
        4,
        5,
        4,
        3,
        6,
        9,
        8,
        5,
        10,
        0,
        4,
        0,
        0,
        2,
        12
      ],
      "total_amount_usd_by_sdg": [
        480035737.93200004,
        3247141.406,
        618039247.63,
        768490132.9300001,
        136379939.08900002,
        270595117.15999997,
        271677497.657,
        493565493.745,
        848586287.6000001,
        669452320.0410001,
        1319421791.4099998,
        0.0,
        1063980000.8000001,
        0.0,
        0.0,
        135297558.62,
        1338904639.9099998
      ]
    },
    "2025": {
      "project_count_by_sdg": [
        8,
        3,
        5,
        9,
        4,
        2,
        1,
        17,
        13,
        7,
        16,
        0,
        4,
        0,
        0,
        0,
        6
      ],
      "total_amount_usd_by_sdg": [
        859410092.3040001,
        127720895.34,
        344738179.29,
        859410092.22,
        178592777.374,
        159109928.95,
        21647609.38,
        860492472.698,
        954659573.4300001,
        722488962.88,
        1667948302.4699998,
        0.0,
        800961546.9300001,
        0.0,
        0.0,
        0.0,
        963318617.1700001
      ]
    }
  },
  "pipeline_version": "v2",
  "source_csv": "MDB_2016-2025_SDG_results_1-29008.csv"
}